{
    "thriftwood.Add": "Adicionar",
    "thriftwood.Alpha": "Alpha",
    "thriftwood.AnErrorHasOccurred": "Ocorreu um erro",
    "thriftwood.Ascending": "Ascendente",
    "thriftwood.BackUp": "Back Up",
    "thriftwood.Beta": "Beta",
    "thriftwood.BlockView": "Visualização em bloco",
    "thriftwood.BuyMeABeer": "Compre-me uma cerveja",
    "thriftwood.BuyMeABurger": "Compre-me um hambúrguer",
    "thriftwood.BuyMeACoffee": "Compre-me um café",
    "thriftwood.BuyMeASoda": "Compre-me um refrigerante",
    "thriftwood.Cancel": "Cancelar",
    "thriftwood.ChangeProfiles": "Mudar de Perfil",
    "thriftwood.Changelog": "Alterações",
    "thriftwood.CheckLogsMessage": "Verifique os registos para mais detalhes",
    "thriftwood.Clear": "Limpar",
    "thriftwood.Close": "Fechar",
    "thriftwood.ComingSoon": "Em Breve",
    "thriftwood.Copied": "Copiado",
    "thriftwood.CopiedContentToTheClipboard": "Conteúdo copiado para a área de transferência",
    "thriftwood.Critical": "Crítico",
    "thriftwood.Dashboard": "Painel de Controle",
    "thriftwood.Days": "{} Dias",
    "thriftwood.DaysAgo": "{} Dias atrás",
    "thriftwood.Debug": "Depurar",
    "thriftwood.Delete": "Eliminar",
    "thriftwood.Descending": "Descendente",
    "thriftwood.Develop": "Desenvolver",
    "thriftwood.Disable": "Desativar",
    "thriftwood.Disabled": "Desativado",
    "thriftwood.Dismiss": "Dispensar",
    "thriftwood.Edge": "Edge",
    "thriftwood.Error": "Erro",
    "thriftwood.ExternalModules": "Módulos Externos",
    "thriftwood.Features": "Recursos",
    "thriftwood.Fixes": "Correções",
    "thriftwood.FullChangelog": "Registro de alterações completo",
    "thriftwood.GoBack": "Voltar",
    "thriftwood.GoToSettings": "Ir para as Definições",
    "thriftwood.GridView": "Visualização em Grade",
    "thriftwood.Home": "Home",
    "thriftwood.Hours": "{} Horas",
    "thriftwood.HoursAgo": "{} Horas atrás",
    "thriftwood.IncorrectEncryptionKey": "Chave de encriptação incorreta",
    "thriftwood.Internal": "Interno",
    "thriftwood.InvalidFileTypeSelected": "Tipo de arquivo selecionado inválido",
    "thriftwood.Items": "{} Itens",
    "thriftwood.JustNow": "Agora mesmo",
    "thriftwood.Minutes": "{} Minutos",
    "thriftwood.MinutesAgo": "{} Minutos atrás",
    "thriftwood.Module": "Módulo",
    "thriftwood.ModuleIsNotEnabled": "{} Não Está Ativo",
    "thriftwood.Months": "{} Meses",
    "thriftwood.MonthsAgo": "{} Meses atrás",
    "thriftwood.New": "Novo",
    "thriftwood.No": "Não",
    "thriftwood.NoModulesEnabled": "Nenhum Módulo Ativado",
    "thriftwood.NotSet": "Não Definido",
    "thriftwood.OneDay": "1 Dia",
    "thriftwood.OneDayAgo": "1 Dia atrás",
    "thriftwood.OneHour": "1 Hora",
    "thriftwood.OneHourAgo": "1 Hora atrás",
    "thriftwood.OneItem": "1 Item",
    "thriftwood.OneMinute": "1 Minuto",
    "thriftwood.OneMinuteAgo": "1 Minuto atrás",
    "thriftwood.OneMonth": "1 Mês",
    "thriftwood.OneMonthAgo": "1 Mês atrás",
    "thriftwood.OneSecond": "1 Segundo",
    "thriftwood.OneSecondAgo": "1 Segundo atrás",
    "thriftwood.OneYear": "1 Ano",
    "thriftwood.OneYearAgo": "1 Ano atrás",
    "thriftwood.Options": "Opções",
    "thriftwood.Other": "Outro",
    "thriftwood.Page": "Página",
    "thriftwood.PlatformSpecific": "Específico da plataforma",
    "thriftwood.PleaseTryAgain": "Por favor, tente novamente",
    "thriftwood.Production": "Produção",
    "thriftwood.Refresh": "Atualizar",
    "thriftwood.Refreshing": "Atualizando…",
    "thriftwood.Remove": "Remover",
    "thriftwood.Rename": "Renomear",
    "thriftwood.Restore": "Restaurar",
    "thriftwood.Retry": "Repetir",
    "thriftwood.ReturnToDashboard": "Voltar ao painel de aplicações",
    "thriftwood.SearchTextBar": "Procurar…",
    "thriftwood.Seconds": "{} Segundos",
    "thriftwood.SecondsAgo": "{} Segundos atrás",
    "thriftwood.Set": "Definir",
    "thriftwood.Settings": "Definições",
    "thriftwood.Stable": "Estável",
    "thriftwood.ThankYou": "Obrigado",
    "thriftwood.Today": "Hoje",
    "thriftwood.TransactionFailure": "Falha na transação",
    "thriftwood.TryAgain": "Tente novamente",
    "thriftwood.Tweaks": "Ajustes",
    "thriftwood.UnderAMinute": "Em menos de um minuto",
    "thriftwood.Unknown": "Desconhecido",
    "thriftwood.UnknownDate": "Data Desconhecida",
    "thriftwood.UnknownError": "Erro Desconhecido",
    "thriftwood.UnknownModule": "Módulo Desconhecido",
    "thriftwood.Update": "Atualizar",
    "thriftwood.View": "Visão",
    "thriftwood.Warning": "Aviso",
    "thriftwood.Website": "Website",
    "thriftwood.Years": "{} Anos",
    "thriftwood.YearsAgo": "{} Anos atrás",
    "thriftwood.Yes": "Sim"
}
